sarina/__init__.py
sarina/cli/__init__.py
sarina/cli/cluster.py
sarina/cli/domain.py
sarina/cli/fix.py
sarina/cli/key.py
sarina/cli/main.py
sarina/cli/monitoring.py
sarina/cli/provider.py
sarina/cli/server.py
sarina/cli/util.py
sarina/core/__init__.py
sarina/core/config.py
sarina/core/logging.py
sarina/core/task.py
sarina/core/utils.py
sarina/monitoring/__init__.py
sarina/monitoring/dashboard_overview.py
sarina/monitoring/dashboard_traffic.py
sarina/monitoring/monitoring.py
sarina/providers/__init__.py
sarina/providers/arvan.py
sarina/providers/base.py
sarina/providers/digitalocean.py
sarina/templates/__init__.py
sarina/templates/base.py
sarina/templates/ss_v2ray_plugin.py
sarina/templates/v2ray_ws_tls_noaead.py
sarina-0.0.2.dist-info/entry_points.txt
sarina-0.0.2.dist-info/WHEEL
sarina-0.0.2.dist-info/METADATA
sarina-0.0.2.dist-info/RECORD
