Metadata-Version: 2.1
Name: sarina
Version: 0.0.2
Summary: 
Author: Hadi
Author-email: hadi.zolfaghaari@gmail.com
Requires-Python: >=3.8,<4.0
Classifier: Programming Language :: Python :: 3
Classifier: Programming Language :: Python :: 3.8
Classifier: Programming Language :: Python :: 3.9
Classifier: Programming Language :: Python :: 3.10
Classifier: Programming Language :: Python :: 3.11
Requires-Dist: deepdiff (>=6.2.1,<7.0.0)
Requires-Dist: inquirerpy (>=0.3.4,<0.4.0)
Requires-Dist: paramiko (>=2.12.0,<3.0.0)
Requires-Dist: python-digitalocean (>=1.17.0,<2.0.0)
Requires-Dist: pyyaml (>=6.0,<7.0)
Requires-Dist: rich (>=12.6.0,<13.0.0)
Requires-Dist: tld (>=0.12.6,<0.13.0)
Requires-Dist: tqdm (>=4.60.0,<5.0.0)
